civitconfig/__init__.py
civitconfig/__main__.py
civitconfig/args/argparser.py
civitconfig/data/__init__.py
civitconfig/data/configmanager.py
civitconfig/data/config/__init__.py
civitconfig/data/config/aliasconfig.py
civitconfig/data/config/config.py
civitconfig/data/config/defaultconfig.py
civitconfig/data/config/sorterconfig.py
civitdl/__init__.py
civitdl/__main__.py
civitdl/api/sorter.py
civitdl/args/argparser.py
civitdl/batch/_metadata.py
civitdl/batch/_model.py
civitdl/batch/batch_download.py
civitmisc/__init__.py
civitmisc/__main__.py
civitmisc/args/argparser.py
helpers/__init__.py
helpers/argparse.py
helpers/cache.py
helpers/options.py
helpers/sourcemanager.py
helpers/core/__Init__.py
helpers/core/_validation.py
helpers/core/constants.py
helpers/core/iohelper.py
helpers/core/utils.py
helpers/core/_ui/__Init__.py
helpers/core/_ui/styler.py
helpers/sorter/__Init__.py
helpers/sorter/basic.py
helpers/sorter/tags.py
helpers/sorter/utils.py
civitdl-2.1.2.dist-info/METADATA
civitdl-2.1.2.dist-info/WHEEL
civitdl-2.1.2.dist-info/entry_points.txt
civitdl-2.1.2.dist-info/top_level.txt
civitdl-2.1.2.dist-info/RECORD
