Metadata-Version: 2.4
Name: civitdl
Version: 2.1.2
Summary: Package for batch downloading models from civitai.com
Author: Owen Truong
License:                                  Apache License
Project-URL: Repository, https://github.com/OwenTruong/civitdl
Project-URL: Bug Tracker, https://github.com/OwenTruong/civitdl/issues
Keywords: civitai,batch download
Classifier: Programming Language :: Python :: 3.8
Classifier: License :: OSI Approved :: Apache Software License
Classifier: Operating System :: OS Independent
Requires-Python: >=3.8
Requires-Dist: requests<3,>=2.31.0
Requires-Dist: tqdm<5,>=4.66.1
Requires-Dist: appdirs<2,>=1.4.4
Requires-Dist: argparse<2,>=1.4
